peakoscope/__init__.py
peakoscope/__main__.py
peakoscope/data.py
peakoscope/errors.py
peakoscope/formats.py
peakoscope/interface_matplotlib.py
peakoscope/interface_pandas.py
peakoscope/interface_polars.py
peakoscope/peaks.py
peakoscope/testing.py
peakoscope/trees.py
peakoscope/utilities.py
peakoscope-1.1.0.dist-info/licenses/LICENSE
peakoscope-1.1.0.dist-info/METADATA
peakoscope-1.1.0.dist-info/WHEEL
peakoscope-1.1.0.dist-info/top_level.txt
peakoscope-1.1.0.dist-info/RECORD
