Metadata-Version: 2.4
Name: peakoscope
Version: 1.1.0
Summary: Data analysis of peak and valley regions
Author-email: Eivind Tøstesen <contact@tostesen.no>
License-Expression: GPL-3.0-or-later
Project-URL: Homepage, https://github.com/eivindtostesen/hierarchical_peak_finding
Project-URL: Issues, https://github.com/eivindtostesen/hierarchical_peak_finding/issues
Keywords: peak,valley,time series,nested,regions,hierarchical,data analysis,random walk,feature extraction
Classifier: Programming Language :: Python
Classifier: Programming Language :: Python :: 3
Classifier: Operating System :: OS Independent
Classifier: Intended Audience :: Science/Research
Classifier: Intended Audience :: Developers
Classifier: Topic :: Scientific/Engineering
Classifier: Topic :: Scientific/Engineering :: Mathematics
Classifier: Topic :: Scientific/Engineering :: Visualization
Classifier: Topic :: Software Development :: Libraries :: Python Modules
Requires-Python: >=3.8
License-File: LICENSE
Provides-Extra: matplotlib
Requires-Dist: matplotlib>=3.4.1; extra == "matplotlib"
Provides-Extra: pandas
Requires-Dist: pandas>=1.3.0; extra == "pandas"
Provides-Extra: polars
Requires-Dist: polars>=0.17.0; extra == "polars"
Provides-Extra: test
Requires-Dist: pytest>=8.1.1; extra == "test"
Requires-Dist: pytest-cov>=5.0.0; extra == "test"
Dynamic: license-file
